{"cameraMode":{"drawMode":0,"name":"Shaded","section":"Shading Mode"},"sceneLighting":true,"audioPlay":false,"sceneViewState":{"showFog":true,"showMaterialUpdate":false,"showSkybox":true,"showFlares":true,"showImageEffects":true,"showParticleSystems":true},"in2DMode":false,"pivot":{"x":94.8266830444336,"y":20.65797996520996,"z":19.622650146484376},"rotation":{"x":0.0013871063711121679,"y":0.642299234867096,"z":-0.001162198488600552,"w":0.7664523124694824},"size":147.19618225097657,"orthographic":false}